packaging_extrapolation/Extrapolation.py
packaging_extrapolation/UtilLog.py
packaging_extrapolation/UtilTools.py
packaging_extrapolation/UtilTools_test.py
packaging_extrapolation/Util_txt.py
packaging_extrapolation/__init__.py
packaging_extrapolation/my_UtilTools.py
packaging_extrapolation-1.1.0.dist-info/LICENSE
packaging_extrapolation-1.1.0.dist-info/METADATA
packaging_extrapolation-1.1.0.dist-info/WHEEL
packaging_extrapolation-1.1.0.dist-info/top_level.txt
packaging_extrapolation-1.1.0.dist-info/RECORD
