Metadata-Version: 2.1
Name: packaging-extrapolation
Version: 1.1.0
Summary: Extrapolation methods for complete basis sets
Author-email: ZHAOKAI XI <xizaokaiz@foxmail.com>
License: MIT License
Project-URL: Repository, https://github.com/xizaokaiz/packaging_extrapolation.git
Keywords: basis set,extrapolation,quantum chemistry
Classifier: Programming Language :: Python :: 3
Classifier: License :: OSI Approved :: MIT License
Classifier: Operating System :: OS Independent
Requires-Python: >=3.6
License-File: LICENSE
Requires-Dist: numpy
Requires-Dist: pandas
Requires-Dist: scipy
Requires-Dist: scikit-learn
Requires-Dist: matplotlib
